azure/monitor/ingestion/__init__.py
azure/monitor/ingestion/_client.py
azure/monitor/ingestion/_configuration.py
azure/monitor/ingestion/_helpers.py
azure/monitor/ingestion/_models.py
azure/monitor/ingestion/_patch.py
azure/monitor/ingestion/_serialization.py
azure/monitor/ingestion/_vendor.py
azure/monitor/ingestion/_version.py
azure/monitor/ingestion/py.typed
azure/monitor/ingestion/_operations/__init__.py
azure/monitor/ingestion/_operations/_operations.py
azure/monitor/ingestion/_operations/_patch.py
azure/monitor/ingestion/aio/__init__.py
azure/monitor/ingestion/aio/_client.py
azure/monitor/ingestion/aio/_configuration.py
azure/monitor/ingestion/aio/_patch.py
azure/monitor/ingestion/aio/_vendor.py
azure/monitor/ingestion/aio/_operations/__init__.py
azure/monitor/ingestion/aio/_operations/_operations.py
azure/monitor/ingestion/aio/_operations/_patch.py
azure_monitor_ingestion-1.0.4.dist-info/LICENSE
azure_monitor_ingestion-1.0.4.dist-info/METADATA
azure_monitor_ingestion-1.0.4.dist-info/WHEEL
azure_monitor_ingestion-1.0.4.dist-info/top_level.txt
azure_monitor_ingestion-1.0.4.dist-info/RECORD
